gguf_quantization/__init__.py
gguf_quantization/quantize.py
gguf_quantization/upload_to_hf.py
gguf_quantization/utils.py
gguf_quantization-0.1.0.dist-info/METADATA
gguf_quantization-0.1.0.dist-info/WHEEL
gguf_quantization-0.1.0.dist-info/top_level.txt
gguf_quantization-0.1.0.dist-info/RECORD
